logscale/__init__.py
logscale/_version.py
logscale/_version.pyi
logscale/order_of_magnitude.py
logscale-0.1.1.dist-info/METADATA
logscale-0.1.1.dist-info/WHEEL
logscale-0.1.1.dist-info/licenses/LICENSE
logscale-0.1.1.dist-info/RECORD
