Metadata-Version: 2.4
Name: logscale
Version: 0.1.1
Summary: Compute orders of magnitude
Project-URL: Homepage, https://github.com/cyrraz/logscale
Author-email: cyrraz <code.cyrraz@protonmail.com>
License-File: LICENSE
Requires-Python: >=3.9
